selberai/__init__.py
selberai/data/__init__.py
selberai/data/download_data.py
selberai/data/load_data.py
selberai/data/upload_data.py
selberai-0.0.0.dist-info/METADATA
selberai-0.0.0.dist-info/WHEEL
selberai-0.0.0.dist-info/top_level.txt
selberai-0.0.0.dist-info/RECORD
