Metadata-Version: 2.1
Name: selberai
Version: 0.0.0
Summary: Do it Selber... Do it yourself!
Home-page: https://selber.ai
Author: Arsam Aryandoust
Author-email: arsam@mit.edu
Project-URL: Source Code, https://gitlab.com/Selber-AI/selberai
Classifier: Programming Language :: Python :: 3
Classifier: License :: OSI Approved :: MIT License
Classifier: Operating System :: OS Independent
Requires-Dist: numpy >=1.20.0
Requires-Dist: pandas >=1.3.0
